kupala_val/__init__.py
kupala_val/fxforward_sample.csv
kupala_val/main.py
kupala_val/multi_asset_sample.csv
kupala_val/ois_sample.csv
kupala_val/portfolio_analysis.py
kupala_val/sample_data.py
kupala_val-1.1.1.dist-info/licenses/LICENSE
tests/__init__.py
tests/test_kupala_val.py
kupala_val-1.1.1.dist-info/METADATA
kupala_val-1.1.1.dist-info/WHEEL
kupala_val-1.1.1.dist-info/top_level.txt
kupala_val-1.1.1.dist-info/RECORD
