Metadata-Version: 2.4
Name: kupala_val
Version: 1.1.1
Summary: Portfolio valuation, cashflow analysis, and risk assessment.
Home-page: https://github.com/kozyarchuk/kupala_val
Author: Maksim Kozyarchuk
Author-email: maksim.kozyarchuk@gmail.com
Classifier: Programming Language :: Python :: 3
Classifier: License :: OSI Approved :: MIT License
Classifier: Operating System :: OS Independent
Requires-Python: >=3.7
License-File: LICENSE
Requires-Dist: pandas
Requires-Dist: requests
Dynamic: author
Dynamic: author-email
Dynamic: classifier
Dynamic: description
Dynamic: description-content-type
Dynamic: home-page
Dynamic: license-file
Dynamic: requires-dist
Dynamic: requires-python
Dynamic: summary
